cuatrorpc-0.7.2.dist-info/METADATA
cuatrorpc-0.7.2.dist-info/WHEEL
cuatrorpc-0.7.2.dist-info/license_files/LICENSE
cuatrorpc/__init__.pyi
cuatrorpc/__init__.py
cuatrorpc/_async_helper.py
cuatrorpc/cuatrorpc_rs.pyi
cuatrorpc/py.typed
cuatrorpc/cuatrorpc_rs.cpython-312-powerpc64le-linux-gnu.so
cuatrorpc-0.7.2.dist-info/RECORD
