Metadata-Version: 2.1
Name: cuatrorpc
Version: 0.7.2
Classifier: Intended Audience :: Developers
Classifier: License :: OSI Approved :: MIT License
Classifier: Operating System :: MacOS
Classifier: Operating System :: Microsoft :: Windows
Classifier: Operating System :: POSIX :: Linux
Classifier: Programming Language :: Python :: 3
Classifier: Programming Language :: Python :: 3.8
Classifier: Programming Language :: Python :: 3.9
Classifier: Programming Language :: Python :: 3.10
Classifier: Programming Language :: Python :: 3.11
Classifier: Programming Language :: Python :: 3.12
Classifier: Programming Language :: Python :: 3.13
Classifier: Programming Language :: Python :: Implementation :: CPython
Classifier: Programming Language :: Python
Classifier: Programming Language :: Rust
Classifier: Typing :: Typed
License-File: LICENSE
Summary: Fast RPC client library for Python in rust.
Keywords: fast,rpc,bitcoin
Home-Page: https://github.com/bleach86/CuatroRPC
Author: bleach86 <tux@ghostbyjohnmcafee.com>
Author-email: bleach86 <tux@ghostbyjohnmcafee.com>
License: MIT
Requires-Python: >=3.8
Project-URL: Source Code, https://github.com/bleach86/CuatroRPC
